<?xml version="1.0" encoding="utf-8" ?><dwsync><file name=".DS_Store" server="f9-preview.awardspace.net//kristindohn.com/" local="3507849431" remote="319783739158709788" Dst="-1" /><file name=".editorconfig" server="f9-preview.awardspace.net//kristindohn.com/" local="3507827006" remote="319783739158709788" Dst="-1" /><file name=".gitignore" server="f9-preview.awardspace.net//kristindohn.com/" local="3507827006" remote="319783739158709788" Dst="-1" /><file name="bower.json" server="f9-preview.awardspace.net//kristindohn.com/" local="3507827006" remote="319783739158709788" Dst="-1" /><file name="CONTRIBUTING.md" server="f9-preview.awardspace.net//kristindohn.com/" local="3507827006" remote="319783739158709788" Dst="-1" /><file name="eager.jpg" server="f9-preview.awardspace.net//kristindohn.com/" local="3507827006" remote="319783739158709788" Dst="-1" /><file name="Gruntfile.js" server="f9-preview.awardspace.net//kristindohn.com/" local="3507827006" remote="319783739158709788" Dst="-1" /><file name="HISTORY.md" server="f9-preview.awardspace.net//kristindohn.com/" local="3507827006" remote="319783739158709788" Dst="-1" /><file name="hover.jpg" server="f9-preview.awardspace.net//kristindohn.com/" local="3507827006" remote="319783739158709788" Dst="-1" /><file name="index.html" server="f9-preview.awardspace.net//kristindohn.com/" local="3514236715" remote="319783739158709788" Dst="-1" /></dwsync>