<?xml version="1.0" encoding="utf-8" ?><dwsync><file name="404.php" server="f9-preview.awardspace.net//kristindohn.com/" local="3510685710" remote="319783739154564628" Dst="-1" /><file name="ReadMe.txt" server="f9-preview.awardspace.net//kristindohn.com/" local="3510685710" remote="319783739154564628" Dst="-1" /><file name="archive.php" server="f9-preview.awardspace.net//kristindohn.com/" local="3510685711" remote="319783739154564628" Dst="-1" /><file name="attachment.php" server="f9-preview.awardspace.net//kristindohn.com/" local="3510685711" remote="319783739154564628" Dst="-1" /><file name="comments.php" server="f9-preview.awardspace.net//kristindohn.com/" local="3510685712" remote="319783739154564628" Dst="-1" /><file name="content-aside.php" server="f9-preview.awardspace.net//kristindohn.com/" local="3510685718" remote="319783739154564628" Dst="-1" /><file name="content-attachment.php" server="f9-preview.awardspace.net//kristindohn.com/" local="3510685719" remote="319783739154564628" Dst="-1" /><file name="content-page.php" server="f9-preview.awardspace.net//kristindohn.com/" local="3510685720" remote="319783739154564628" Dst="-1" /><file name="content-gallery.php" server="f9-preview.awardspace.net//kristindohn.com/" local="3510685720" remote="319783739154564628" Dst="-1" /><file name="content-search.php" server="f9-preview.awardspace.net//kristindohn.com/" local="3510685720" remote="319783739154564628" Dst="-1" /><file name="content-single.php" server="f9-preview.awardspace.net//kristindohn.com/" local="3510685721" remote="319783739154564628" Dst="-1" /><file name="footer.php" server="f9-preview.awardspace.net//kristindohn.com/" local="3510685721" remote="319783739154564628" Dst="-1" /><file name="content.php" server="f9-preview.awardspace.net//kristindohn.com/" local="3510685721" remote="319783739154564628" Dst="-1" /><file name="functions.php" server="f9-preview.awardspace.net//kristindohn.com/" local="3510685722" remote="319783739154564628" Dst="-1" /><file name="home.php" server="f9-preview.awardspace.net//kristindohn.com/" local="3510685722" remote="319783739154564628" Dst="-1" /><file name="header.php" server="f9-preview.awardspace.net//kristindohn.com/" local="3510685722" remote="319783739154564628" Dst="-1" /><file name="html5.js" server="f9-preview.awardspace.net//kristindohn.com/" local="3510685724" remote="319783739154564628" Dst="-1" /><file name="index.php" server="f9-preview.awardspace.net//kristindohn.com/" local="3510685732" remote="319783739154564628" Dst="-1" /><file name="jquery-migrate-1.1.1.js" server="f9-preview.awardspace.net//kristindohn.com/" local="3510685733" remote="319783739154564628" Dst="-1" /><file name="jquery.js" server="f9-preview.awardspace.net//kristindohn.com/" local="3510685734" remote="319783739154564628" Dst="-1" /><file name="page.php" server="f9-preview.awardspace.net//kristindohn.com/" local="3510685745" remote="319783739154564628" Dst="-1" /><file name="screenshot.png" server="f9-preview.awardspace.net//kristindohn.com/" local="3510685745" remote="319783739154564628" Dst="-1" /><file name="script.responsive.js" server="f9-preview.awardspace.net//kristindohn.com/" local="3510685747" remote="319783739154564628" Dst="-1" /><file name="search.php" server="f9-preview.awardspace.net//kristindohn.com/" local="3510685748" remote="319783739154564628" Dst="-1" /><file name="script.js" server="f9-preview.awardspace.net//kristindohn.com/" local="3510685748" remote="319783739154564628" Dst="-1" /><file name="sidebar-bottom.php" server="f9-preview.awardspace.net//kristindohn.com/" local="3510685749" remote="319783739154564628" Dst="-1" /><file name="sidebar-footer.php" server="f9-preview.awardspace.net//kristindohn.com/" local="3510685749" remote="319783739154564628" Dst="-1" /><file name="searchform.php" server="f9-preview.awardspace.net//kristindohn.com/" local="3510685749" remote="319783739154564628" Dst="-1" /><file name="sidebar-nav.php" server="f9-preview.awardspace.net//kristindohn.com/" local="3510685750" remote="319783739154564628" Dst="-1" /><file name="sidebar-top.php" server="f9-preview.awardspace.net//kristindohn.com/" local="3510685750" remote="319783739154564628" Dst="-1" /><file name="sidebar-header.php" server="f9-preview.awardspace.net//kristindohn.com/" local="3510685750" remote="319783739154564628" Dst="-1" /><file name="sidebar.php" server="f9-preview.awardspace.net//kristindohn.com/" local="3510685751" remote="319783739154564628" Dst="-1" /><file name="single.php" server="f9-preview.awardspace.net//kristindohn.com/" local="3510685751" remote="319783739154564628" Dst="-1" /><file name="style.ie7.css" server="f9-preview.awardspace.net//kristindohn.com/" local="3510685752" remote="319783739154564628" Dst="-1" /><file name="style.responsive.css" server="f9-preview.awardspace.net//kristindohn.com/" local="3510685752" remote="319783739154564628" Dst="-1" /><file name="style.css" server="f9-preview.awardspace.net//kristindohn.com/" local="3510685752" remote="319783739154564628" Dst="-1" /></dwsync>